render_svg_icons/LICENSE
render_svg_icons/__init__.py
render_svg_icons/dependencies.py
render_svg_icons/output.py
render_svg_icons/parse_svg.py
render_svg_icons/png.py
render_svg_icons/render.py
render_svg_icons/render_category.py
render_svg_icons-0.1.0.dist-info/entry_points.txt
render_svg_icons-0.1.0.dist-info/WHEEL
render_svg_icons-0.1.0.dist-info/METADATA
render_svg_icons-0.1.0.dist-info/RECORD
