Metadata-Version: 2.1
Name: render-svg-icons
Version: 0.1.0
Summary: Python script to render SVG icons to PNG icons in various sizes
Home-page: https://github.com/elsiehupp/render-svg-icons
License: GPL-3.0-or-later
Keywords: Icons,Inkscape,Linux,SVG
Author: GNOME icon developers
Maintainer: Elsie Hupp
Maintainer-email: github@elsiehupp.com
Requires-Python: >=3.8,<4.0
Classifier: Development Status :: 4 - Beta
Classifier: Intended Audience :: Developers
Classifier: License :: OSI Approved :: GNU General Public License v3 or later (GPLv3+)
Classifier: Natural Language :: English
Classifier: Operating System :: MacOS :: MacOS X
Classifier: Operating System :: POSIX :: Linux
Classifier: Programming Language :: Python :: 3
Classifier: Programming Language :: Python :: 3 :: Only
Classifier: Programming Language :: Python :: 3.8
Classifier: Programming Language :: Python :: 3.9
Classifier: Topic :: Artistic Software
Classifier: Topic :: Desktop Environment :: File Managers
Classifier: Topic :: Multimedia :: Graphics
Classifier: Topic :: Software Development :: User Interfaces
Classifier: Topic :: System :: Shells
Classifier: Topic :: Utilities
Project-URL: Repository, https://github.com/elsiehupp/render-svg-icons
